[
  {
    "firstName": "Ethan",
    "lastName": "Martinez",
    "birthDay": "1999-05-05",
    "subscription": "1month, spa"
  },
  {
    "firstName": "Mia",
    "lastName": "Clark",
    "birthDay": "1997-02-10",
    "subscription": "3months, sauna, massage"
  },
  {
    "firstName": "Liam",
    "lastName": "Taylor",
    "birthDay": "1998-07-15",
    "subscription": "6months, spa, massage"
  },
  {
    "firstName": "Charlotte",
    "lastName": "Brown",
    "birthDay": "1996-02-20",
    "subscription": "1year, sauna, massage"
  },
  {
    "firstName": "Ava",
    "lastName": "Johnson",
    "birthDay": "1999-07-25",
    "subscription": "single session, spa, massage"
  },
  {
    "firstName": "James",
    "lastName": "Garcia",
    "birthDay": "1996-03-01",
    "subscription": "1month, sauna"
  },
  {
    "firstName": "Sophia",
    "lastName": "Davis",
    "birthDay": "1998-08-05",
    "subscription": "3months, spa, massage"
  },
  {
    "firstName": "Oliver",
    "lastName": "Young",
    "birthDay": "1997-03-10",
    "subscription": "6months, sauna, massage"
  },
  {
    "firstName": "Emma",
    "lastName": "Martinez",
    "birthDay": "1996-11-15",
    "subscription": "1year, spa, massage"
  },
  {
    "firstName": "Ethan",
    "lastName": "Brown",
    "birthDay": "1999-06-20",
    "subscription": "single session, sauna, massage"
  },
  {
    "firstName": "Mia",
    "lastName": "Hernandez",
    "birthDay": "1997-01-25",
    "subscription": "1month, spa, massage"
  },
  {
    "firstName": "Liam",
    "lastName": "Garcia",
    "birthDay": "1998-06-30",
    "subscription": "3months, sauna"
  },
  {
    "firstName": "Charlotte",
    "lastName": "Clark",
    "birthDay": "1996-12-05",
    "subscription": "6months, spa, massage"
  },
  {
    "firstName": "Ava",
    "lastName": "Taylor",
    "birthDay": "1999-07-10",
    "subscription": "1year, sauna, massage"
  },
  {
    "firstName": "James",
    "lastName": "Brown",
    "birthDay": "1996-02-15",
    "subscription": "single session, spa, massage"
  },
  {
    "firstName": "Sophia",
    "lastName": "Johnson",
    "birthDay": "1998-07-20",
    "subscription": "1month, sauna"
  },
  {
    "firstName": "Oliver",
    "lastName": "Davis",
    "birthDay": "1997-03-25",
    "subscription": "3months, spa, massage"
  },
  {
    "firstName": "Emma",
    "lastName": "Young",
    "birthDay": "1996-10-30",
    "subscription": "6months, sauna, massage"
  },
  {
    "firstName": "Ethan",
    "lastName": "Martinez",
    "birthDay": "1999-05-05",
    "subscription": "1year, spa, massage"
  },
  {
    "firstName": "Mia",
    "lastName": "Clark",
    "birthDay": "1997-02-10",
    "subscription": "single session, sauna"
  },
  {
    "firstName": "Liam",
    "lastName": "Taylor",
    "birthDay": "1998-07-15",
    "subscription": "1month, spa, massage"
  },
  {
    "firstName": "Charlotte",
    "lastName": "Brown",
    "birthDay": "1996-02-20",
    "subscription": "3months, sauna, massage"
  },
  {
    "firstName": "Ava",
    "lastName": "Johnson",
    "birthDay": "1999-07-25",
    "subscription": "6months, spa"
  },
  {
    "firstName": "James",
    "lastName": "Garcia",
    "birthDay": "1996-03-01",
    "subscription": "1year, sauna, massage"
  },
  {
    "firstName": "Sophia",
    "lastName": "Davis",
    "birthDay": "1998-08-05",
    "subscription": "single session, spa, massage"
  },
  {
    "firstName": "Oliver",
    "lastName": "Young",
    "birthDay": "1997-03-10",
    "subscription": "1month, sauna"
  },
  {
    "firstName": "Emma",
    "lastName": "Martinez",
    "birthDay": "1996-11-15",
    "subscription": "3months, spa, massage"
  },
  {
    "firstName": "Ethan",
    "lastName": "Brown",
    "birthDay": "1999-06-20",
    "subscription": "6months, sauna, massage"
  },
  {
    "firstName": "Mia",
    "lastName": "Hernandez",
    "birthDay": "1997-01-25",
    "subscription": "1year, spa, massage"
  },
  {
    "firstName": "Liam",
    "lastName": "Garcia",
    "birthDay": "1998-06-30",
    "subscription": "single session, sauna, massage"
  },
  {
    "firstName": "Charlotte",
    "lastName": "Clark",
    "birthDay": "1996-12-05",
    "subscription": "1month, spa"
  },
  {
    "firstName": "Ava",
    "lastName": "Taylor",
    "birthDay": "1999-07-10",
    "subscription": "3months, sauna, massage"
  },
  {
    "firstName": "James",
    "lastName": "Brown",
    "birthDay": "1996-02-15",
    "subscription": "6months, spa, massage"
  },
  {
    "firstName": "Sophia",
    "lastName": "Johnson",
    "birthDay": "1998-07-20",
    "subscription": "1year, sauna, massage"
  },
  {
    "firstName": "Oliver",
    "lastName": "Davis",
    "birthDay": "1997-03-25",
    "subscription": "single session, spa, massage"
  },
  {
    "firstName": "Emma",
    "lastName": "Young",
    "birthDay": "1996-10-30",
    "subscription": "1month, sauna"
  },
  {
    "firstName": "Ethan",
    "lastName": "Martinez",
    "birthDay": "1999-05-05",
    "subscription": "3months, spa, massage"
  },
  {
    "firstName": "Mia",
    "lastName": "Clark",
    "birthDay": "1997-02-10",
    "subscription": "6months, sauna, massage"
  },
  {
    "firstName": "Liam",
    "lastName": "Taylor",
    "birthDay": "1998-07-15",
    "subscription": "1year, spa"
  },
  {
    "firstName": "Charlotte",
    "lastName": "Brown",
    "birthDay": "1996-02-20",
    "subscription": "single session, sauna, massage"
  },
  {
    "firstName": "Ava",
    "lastName": "Johnson",
    "birthDay": "1999-07-25",
    "subscription": "1month, spa, massage"
  },
  {
    "firstName": "James",
    "lastName": "Garcia",
    "birthDay": "1996-03-01",
    "subscription": "3months, sauna"
  },
  {
    "firstName": "Sophia",
    "lastName": "Davis",
    "birthDay": "1998-08-05",
    "subscription": "6months, spa, massage"
  },
  {
    "firstName": "Oliver",
    "lastName": "Young",
    "birthDay": "1997-03-10",
    "subscription": "1year, sauna, massage"
  },
  {
    "firstName": "Emma",
    "lastName": "Martinez",
    "birthDay": "1996-11-15",
    "subscription": "single session, spa, massage"
  },
  {
    "firstName": "Ethan",
    "lastName": "Brown",
    "birthDay": "1999-06-20",
    "subscription": "1month, sauna"
  },
  {
    "firstName": "Mia",
    "lastName": "Hernandez",
    "birthDay": "1997-01-25",
    "subscription": "3months, spa, massage"
  },
  {
    "firstName": "Liam",
    "lastName": "Garcia",
    "birthDay": "1998-06-30",
    "subscription": "6months, sauna, massage"
  },
  {
    "firstName": "Charlotte",
    "lastName": "Clark",
    "birthDay": "1996-12-05",
    "subscription": "1year, spa, massage"
  },
  {
    "firstName": "Ava",
    "lastName": "Taylor",
    "birthDay": "1999-07-10",
    "subscription": "single session, sauna"
  },
  {
    "firstName": "James",
    "lastName": "Brown",
    "birthDay": "1996-02-15",
    "subscription": "1month, spa, massage"
  }
]
